agentical/__init__.py
agentical/_version.py
agentical/chat_client.py
agentical/logging_config.py
agentical/api/__init__.py
agentical/api/llm_backend.py
agentical/llm/anthropic/__init__.py
agentical/llm/anthropic/anthropic_chat.py
agentical/llm/anthropic/schema_adapter.py
agentical/llm/gemini/__init__.py
agentical/llm/gemini/gemini_chat.py
agentical/llm/gemini/schema_adapter.py
agentical/llm/openai/__init__.py
agentical/llm/openai/openai_chat.py
agentical/llm/openai/schema_adapter.py
agentical/mcp/__init__.py
agentical/mcp/config.py
agentical/mcp/connection.py
agentical/mcp/health.py
agentical/mcp/prompt_registry.py
agentical/mcp/provider.py
agentical/mcp/resource_registry.py
agentical/mcp/schemas.py
agentical/mcp/tool_registry.py
agentical/utils/log_utils.py
beanone_agentical-0.3.2.dist-info/METADATA
beanone_agentical-0.3.2.dist-info/WHEEL
beanone_agentical-0.3.2.dist-info/RECORD
