Metadata-Version: 2.4
Name: beanone-agentical
Version: 0.3.2
Summary: MCP-Compliant LLM Integration Framework
Project-URL: Homepage, https://github.com/agentical/agentical
Project-URL: Documentation, https://github.com/agentical/agentical#readme
Project-URL: Repository, https://github.com/agentical/agentical.git
Project-URL: Issues, https://github.com/agentical/agentical/issues
Author-email: Beanone Team <beanone@example.com>
License-Expression: MIT
Keywords: ai,integration,llm,mcp,tools
Classifier: Development Status :: 3 - Alpha
Classifier: Intended Audience :: Developers
Classifier: License :: OSI Approved :: MIT License
Classifier: Programming Language :: Python :: 3
Classifier: Programming Language :: Python :: 3.10
Classifier: Programming Language :: Python :: 3.11
Classifier: Topic :: Scientific/Engineering :: Artificial Intelligence
Classifier: Topic :: Software Development :: Libraries :: Python Modules
Requires-Python: >=3.10
Requires-Dist: aiohttp>=3.0.0
Requires-Dist: anthropic>=0.3.0
Requires-Dist: backoff>=2.2.1
Requires-Dist: google-cloud-aiplatform>=1.36.0
Requires-Dist: google-genai>=0.2.0
Requires-Dist: google-generativeai>=0.3.0
Requires-Dist: mcp>=0.1.0
Requires-Dist: openai>=1.0.0
Requires-Dist: presidio-analyzer>=2.2.33
Requires-Dist: presidio-anonymizer>=2.2.33
Requires-Dist: pydantic>=2.0.0
Requires-Dist: python-dotenv>=1.0.0
Provides-Extra: dev
Requires-Dist: aiohttp>=3.8.4; extra == 'dev'
Requires-Dist: black>=23.0.0; extra == 'dev'
Requires-Dist: build>=1.0.0; extra == 'dev'
Requires-Dist: mypy>=1.0.0; extra == 'dev'
Requires-Dist: pytest-asyncio>=0.21.0; extra == 'dev'
Requires-Dist: pytest-cov>=4.1.0; extra == 'dev'
Requires-Dist: pytest>=7.0.0; extra == 'dev'
Requires-Dist: ruff>=0.1.0; extra == 'dev'
Requires-Dist: twine>=4.0.0; extra == 'dev'
